cdk_log_notifier/__init__.py
cdk_log_notifier/py.typed
cdk_log_notifier/_jsii/__init__.py
cdk_log_notifier/_jsii/cdk-log-notifier@2.2.0.jsii.tgz
cdk_log_notifier-2.2.0.dist-info/LICENSE
cdk_log_notifier-2.2.0.dist-info/METADATA
cdk_log_notifier-2.2.0.dist-info/WHEEL
cdk_log_notifier-2.2.0.dist-info/top_level.txt
cdk_log_notifier-2.2.0.dist-info/RECORD
