Metadata-Version: 2.1
Name: cdk-log-notifier
Version: 2.2.0
Summary: @thedesignium/cdk-log-notifier
Home-page: https://github.com/TheDesignium/cdk-log-notifier.git
Author: Yuki Ito
License: MIT
Project-URL: Source, https://github.com/TheDesignium/cdk-log-notifier.git
Classifier: Intended Audience :: Developers
Classifier: Operating System :: OS Independent
Classifier: Programming Language :: JavaScript
Classifier: Programming Language :: Python :: 3 :: Only
Classifier: Programming Language :: Python :: 3.8
Classifier: Programming Language :: Python :: 3.9
Classifier: Programming Language :: Python :: 3.10
Classifier: Programming Language :: Python :: 3.11
Classifier: Typing :: Typed
Classifier: License :: OSI Approved
Requires-Python: ~=3.8
License-File: LICENSE
Requires-Dist: aws-cdk-lib<3.0.0,>=2.150.0
Requires-Dist: constructs<11.0.0,>=10.3.0
Requires-Dist: jsii<2.0.0,>=1.101.0
Requires-Dist: publication>=0.0.3
Requires-Dist: typeguard~=2.13.3
